{
    "users": [
      {
        "id": 1,
        "name": "John Doe",
        "image": "https://img-b.udemycdn.com/course/480x270/2776760_f176_10.jpg",
        "email": "john.doe@example.com"
      },
      {
        "id": 2,
        "name": "Ann Mary",
        "image": "https://media.istockphoto.com/id/1475804411/photo/smiling-young-hispanic-self-employed-woman-standing-in-studio-with-laptop-in-hand.jpg?s=1024x1024&w=is&k=20&c=Nlzxn5uGC1jxcAL7b_VB0qwlIkGNTMdD0JhwBJJVdLI=",
        "email": "a.mary@example.com"
      },
      {
        "id": 3,
        "name": "Bob The Builder",
        "image": "https://images.pexels.com/photos/846741/pexels-photo-846741.jpeg?auto=compress&cs=tinysrgb&w=1260&h=750&dpr=2",
        "email": "bob.builder@example.com"
      },
      {
        "id": 4,
        "name": "Alice Wonderland",
        "image": "https://t3.ftcdn.net/jpg/02/43/12/34/360_F_243123463_zTooub557xEWABDLk0jJklDyLSGl2jrr.jpg",
        "email": "alice.wonderland@example.com"
      },
      {
        "id": 5,
        "name": "Nick Giannopoulos",
        "image": "https://t4.ftcdn.net/jpg/03/83/25/83/360_F_383258331_D8imaEMl8Q3lf7EKU2Pi78Cn0R7KkW9o.jpg",
        "email": "n.giannopoulos@example.com"
      },
      {
        "id": 6,
        "name": "Narayana Garner",
        "image": "https://img-b.udemycdn.com/course/480x270/2776760_f176_10.jpg",
        "email": "n.garner@example.com"
      },
      {
        "id": 7,
        "name": "Anita Gros",
        "image": "https://images.unsplash.com/photo-1544005313-94ddf0286df2?w=800&auto=format&fit=crop&q=60&ixlib=rb-4.0.3&ixid=M3wxMjA3fDB8MHxzZWFyY2h8NHx8cGVyc29ufGVufDB8fDB8fHww",
        "email": "a.gros@example.com"
      },
      {
        "id": 8,
        "name": "Megan Smith",
        "image": "https://images.pexels.com/photos/1222271/pexels-photo-1222271.jpeg?auto=compress&cs=tinysrgb&w=800",
        "email": "m.smith@example.com"
      },
      {
        "id": 9,
        "name": "Unknow Person",
        "image": "https://images.pexels.com/photos/712513/pexels-photo-712513.jpeg?auto=compress&cs=tinysrgb&w=800",
        "email": "u.person@example.com"
      },
      {
        "id": 10,
        "name": "Peter Parker",
        "image": "https://media.istockphoto.com/id/1448331433/photo/portrait-of-a-beautiful-modern-business-woman-using-tablet-in-her-office.jpg?s=1024x1024&w=is&k=20&c=iD4pgN52QoNzUmDsSSphYaNJTerBOx_x7D1rjfEbSZM=",
        "email": "p.parker@example.com"
      },
      {
        "id": 11,
        "name": "Harry Potter",
        "image": "https://images.pexels.com/photos/846741/pexels-photo-846741.jpeg?auto=compress&cs=tinysrgb&w=1260&h=750&dpr=2",
        "email": "h.potter@example.com"
      },
      {
        "id": 12,
        "name": "Jason Bourne",
        "image": "https://img-b.udemycdn.com/course/480x270/2776760_f176_10.jpg",
        "email": "j.bourne@example.com"
      }
    ]
  }
  